.flake8
.gitignore
.gitlab-ci.yml
.pep8speaks.yml
.pre-commit-config.yaml
.readthedocs.yml
CHANGES.rst
LICENSE
MANIFEST.in
README.rst
conftest.py
mypy.ini
pyproject.toml
setup.cfg
setup.py
tox.ini
docs/Makefile
docs/changes.rst
docs/conf.py
docs/examples.rst
docs/index.rst
docs/kanon-logo.png
docs/kanon.ico
docs/make.bat
docs/calendars/index.rst
docs/examples/.gitignore
docs/tables/htable.rst
docs/tables/index.rst
docs/tables/interpolations.rst
docs/tables/symmetries.rst
docs/units/index.rst
docs/units/precision.rst
docs/units/radices.rst
examples/declination.ipynb
examples/ptolemy_viz.ipynb
examples/sun_true_position.ipynb
examples/tests/test_notebooks.py
kanon/__init__.py
kanon/_astropy_init.py
kanon/conftest.py
kanon/py.typed
kanon/version.py
kanon/calendars/__init__.py
kanon/calendars/calendars.py
kanon/calendars/tests/__init__.py
kanon/calendars/tests/test_calendars.py
kanon/extern/__init__.py
kanon/tables/__init__.py
kanon/tables/hcolumn.py
kanon/tables/htable.py
kanon/tables/htable_reader.py
kanon/tables/interpolations.py
kanon/tables/symmetries.py
kanon/tables/tests/__init__.py
kanon/tables/tests/test_hcolumn.py
kanon/tables/tests/test_htable.py
kanon/tables/tests/test_htable_reader.py
kanon/tables/tests/test_interpolations.py
kanon/tables/tests/test_symmetries.py
kanon/tests/__init__.py
kanon/tests/test_based_htable.py
kanon/tests/data/table_content-180.json
kanon/units/__init__.py
kanon/units/precision.py
kanon/units/radices.py
kanon/units/tests/__init__.py
kanon/units/tests/test_basedreal.py
kanon/units/tests/test_precision.py
kanon/units/tests/test_quantity.py
kanon/units/tests/test_radixbase.py
kanon/utils/__init__.py
kanon/utils/list_to_tuple.py
kanon/utils/looping_list.py
kanon/utils/tests/__init__.py
kanon/utils/types/__init__.py
kanon/utils/types/dishas.py
kanon/utils/types/number_types.py
kanonpy.egg-info/PKG-INFO
kanonpy.egg-info/SOURCES.txt
kanonpy.egg-info/dependency_links.txt
kanonpy.egg-info/entry_points.txt
kanonpy.egg-info/not-zip-safe
kanonpy.egg-info/requires.txt
kanonpy.egg-info/top_level.txt
licenses/README.rst
licenses/TEMPLATE_LICENCE.rst