Metadata-Version: 2.1
Name: kanonpy
Version: 0.3.1
Summary: History of astronomy library
Home-page: https://gitlab.obspm.fr/lgauffier/kanon
Author: Kanon Developers
Author-email: lenigauffier@gmail.com
License: BSD 3-Clause
Keywords: astronomy,history,arithmetic,calendars,ptolemy,sexagesimal
Platform: UNKNOWN
Classifier: Intended Audience :: Science/Research
Classifier: License :: OSI Approved :: BSD License
Classifier: Operating System :: OS Independent
Classifier: Development Status :: 4 - Beta
Classifier: Programming Language :: Python :: 3
Classifier: Topic :: Scientific/Engineering :: Astronomy
Classifier: Topic :: Scientific/Engineering :: Mathematics
Classifier: Topic :: Sociology :: History
Requires-Python: >=3.8
Provides-Extra: test
Provides-Extra: docs
License-File: LICENSE
